volcano/iec104srv/__init__.py
volcano/iec104srv/__main__.py
volcano/iec104srv/iec_factory.py
volcano/iec104srv/iec_protocol.py
volcano/iec104srv/iec_server.py
volcano/iec104srv/slave.py
volcano_iec104srv-0.2.1.dist-info/LICENSE
volcano_iec104srv-0.2.1.dist-info/METADATA
volcano_iec104srv-0.2.1.dist-info/WHEEL
volcano_iec104srv-0.2.1.dist-info/top_level.txt
volcano_iec104srv-0.2.1.dist-info/RECORD
