Metadata-Version: 2.1
Name: volcano-iec104srv
Version: 0.2.1
Summary: IEC60870-5-104 server for Volcano
Home-page: UNKNOWN
Author: Vinogradov D
Author-email: dgrapes@gmail.com
License: MIT
Platform: UNKNOWN
Classifier: Programming Language :: Python :: 3
Classifier: License :: OSI Approved :: MIT License
Classifier: Operating System :: OS Independent
Requires-Dist: volcano-general
Requires-Dist: volcano-twistedclient
Requires-Dist: twisted
